pytorch_lr_finder/__init__.py
pytorch_lr_finder/learning_rate_finder.py
tanjid-lr-finder/__init__.py
tanjid-lr-finder/learning_rate_finder.py
tanjid_lr_finder/__init__.py
tanjid_lr_finder/learning_rate_finder.py
pytorch_lr_finder-0.0.3.dist-info/LICENSE
pytorch_lr_finder-0.0.3.dist-info/METADATA
pytorch_lr_finder-0.0.3.dist-info/WHEEL
pytorch_lr_finder-0.0.3.dist-info/top_level.txt
pytorch_lr_finder-0.0.3.dist-info/RECORD
