Metadata-Version: 2.1
Name: pytorch-lr-finder
Version: 0.0.3
Summary: A package for finding optimal learning rate for pytorch models
Home-page: https://github.com/Therap-ML/tanjid-lr-finder
Author: Tanjid Hasan Tonmoy
Author-email: thtonmoy7@gmail.com
License: UNKNOWN
Platform: UNKNOWN
Classifier: Programming Language :: Python :: 3
Classifier: License :: OSI Approved :: MIT License
Classifier: Operating System :: OS Independent
Requires-Python: >=3.6
Requires-Dist: numpy
Requires-Dist: pandas
Requires-Dist: matplotlib
Requires-Dist: torch
